structpp/__init__.py
structpp/format_string.py
structpp/unpack.py
structpp-0.1.0.dist-info/DESCRIPTION.rst
structpp-0.1.0.dist-info/METADATA
structpp-0.1.0.dist-info/RECORD
structpp-0.1.0.dist-info/WHEEL
structpp-0.1.0.dist-info/metadata.json
structpp-0.1.0.dist-info/top_level.txt
